fprettify/__init__.py
fprettify/fparse_utils.py
fprettify-0.3.7.dist-info/LICENSE
fprettify-0.3.7.dist-info/METADATA
fprettify-0.3.7.dist-info/WHEEL
fprettify-0.3.7.dist-info/entry_points.txt
fprettify-0.3.7.dist-info/top_level.txt
fprettify-0.3.7.dist-info/RECORD
