Metadata-Version: 2.1
Name: fprettify
Version: 0.3.7
Summary: auto-formatter for modern fortran source code
Home-page: https://github.com/pseewald/fprettify
Author: Patrick Seewald
Author-email: patrick.seewald@gmail.com
License: GPLv3
Download-URL: https://github.com/pseewald/fprettify/archive/v0.3.7.tar.gz
Keywords: fortran format formatting auto-formatter indent
Platform: UNKNOWN
Classifier: Development Status :: 5 - Production/Stable
Classifier: Intended Audience :: Developers
Classifier: Topic :: Software Development :: Quality Assurance
Classifier: License :: OSI Approved :: GNU General Public License v3 (GPLv3)
Classifier: Programming Language :: Python :: 3
Classifier: Programming Language :: Python :: 3.5
Classifier: Programming Language :: Python :: 3.6
Classifier: Programming Language :: Python :: 3.7
Classifier: Programming Language :: Python :: 3.8
Classifier: Programming Language :: Python :: 3.9
Classifier: Environment :: Console
Classifier: Operating System :: OS Independent
Requires-Dist: configargparse
